<?xml version="1.0" encoding="UTF-8"?>
<!DOCTYPE tiles-definitions PUBLIC 
"-//Apache Software Foundation//DTD Tiles Configuration 3.0//EN" 
"http://tiles.apache.org/dtds/tiles-config_3_0.dtd">

<tiles-definitions>

	<definition name="base.definition" template="/WEB-INF/jsp/admin/common/rrAdminTemplate.jsp">
		<put-attribute name="title" value="Affiliate" />
		<put-attribute name="header" value="/WEB-INF/jsp/admin/common/rrAdminHeader.jsp" />
		<put-attribute name="body" value="" />
		<put-attribute name="footer" value="/WEB-INF/jsp/admin/common/rrAdminFooter.jsp" />
	</definition>



	<definition name="dashboard" extends="base.definition">
		<put-attribute name="body" value="/WEB-INF/jsp/admin/dashboard/dashboard.jsp" />
	</definition>

	<definition name="mgmtdashboard" extends="base.definition">
		<put-attribute name="body" value="/WEB-INF/jsp/admin/dashboard/dashboard.jsp" />
	</definition>

	<definition name="tsdashboard" extends="base.definition">
		<put-attribute name="body" value="/WEB-INF/jsp/admin/dashboard/dashboard.jsp" />
	</definition>

	<definition name="ntsdashboard" extends="base.definition">
		<put-attribute name="body" value="/WEB-INF/jsp/admin/dashboard/dashboard.jsp" />
	</definition>

	<definition name="stddashboard" extends="base.definition">
		<put-attribute name="body" value="/WEB-INF/jsp/admin/dashboard/dashboard.jsp" />
	</definition>

	<definition name="gurddashboard" extends="base.definition">
		<put-attribute name="body" value="/WEB-INF/jsp/admin/dashboard/dashboard.jsp" />
	</definition>



	<definition name="createMenus" extends="base.definition">
		<put-attribute name="body" value="/WEB-INF/jsp/admin/menu/createMenu.jsp" />
	</definition>



	<definition name="createCountry" extends="base.definition">
		<put-attribute name="body" value="/WEB-INF/jsp/admin/country/createCountry.jsp" />
	</definition>



	<definition name="createClass" extends="base.definition">
		<put-attribute name="body" value="/WEB-INF/jsp/admin/class/createClass.jsp" />
	</definition>

	<definition name="updateClass" extends="base.definition">
		<put-attribute name="body" value="/WEB-INF/jsp/admin/class/updateClass.jsp" />
	</definition>



	<definition name="createState" extends="base.definition">
		<put-attribute name="body" value="/WEB-INF/jsp/admin/state/createState.jsp" />
	</definition>

	<definition name="updateState" extends="base.definition">
		<put-attribute name="body" value="/WEB-INF/jsp/admin/state/updateState.jsp" />
	</definition>



	<definition name="createOrganization" extends="base.definition">
		<put-attribute name="body" value="/WEB-INF/jsp/admin/organization/createOrganization.jsp" />
	</definition>

	<definition name="updateOrganization" extends="base.definition">
		<put-attribute name="body" value="/WEB-INF/jsp/admin/organization/updateOrganization.jsp" />
	</definition>

	<definition name="createUserRole" extends="base.definition">
		<put-attribute name="body" value="/WEB-INF/jsp/admin/userRole/createUserRole.jsp" />
	</definition>

	<definition name="updateUserRole" extends="base.definition">
		<put-attribute name="body" value="/WEB-INF/jsp/admin/userRole/updateUserRole.jsp" />
	</definition>


	<definition name="createPermission" extends="base.definition">
		<put-attribute name="body" value="/WEB-INF/jsp/admin/permission/createPermission.jsp" />
	</definition>

	<definition name="updatePermission" extends="base.definition">
		<put-attribute name="body" value="/WEB-INF/jsp/admin/permission/updatePermission.jsp" />
	</definition>





<!--  newly added start -->

	<definition name="createOrder" extends="base.definition">
		<put-attribute name="body" value="/WEB-INF/jsp/admin/order/createOrder.jsp" />
	</definition>

	<definition name="updateOrder" extends="base.definition">
		<put-attribute name="body" value="/WEB-INF/jsp/admin/order/updateOrder.jsp" />
	</definition>

	<definition name="viewOrder" extends="base.definition">
		<put-attribute name="body" value="/WEB-INF/jsp/admin/order/viewOrder.jsp" />
	</definition>

	<definition name="printOrder" extends="base.definition">
		<put-attribute name="body" value="/WEB-INF/jsp/admin/order/printOrder.jsp" />
	</definition>

	<definition name="viewOrders" extends="base.definition">
		<put-attribute name="body" value="/WEB-INF/jsp/admin/order/viewOrders.jsp" />
	</definition>

	<definition name="workList" extends="base.definition">
		<put-attribute name="body" value="/WEB-INF/jsp/admin/order/workList.jsp" />
	</definition>

	<definition name="updateInvoice" extends="base.definition">
		<put-attribute name="body" value="/WEB-INF/jsp/admin/invoice/updateInvoice.jsp" />
	</definition>

<!--  newly added end -->







	<definition name="createUser" extends="base.definition">
		<put-attribute name="body" value="/WEB-INF/jsp/admin/createUser/createUser.jsp" />
	</definition>




	<definition name="emailManagement" extends="base.definition">
		<put-attribute name="body" value="/WEB-INF/jsp/admin/content/emailManagement.jsp" />
	</definition>

	<definition name="addEmail" extends="base.definition">
		<put-attribute name="body" value="/WEB-INF/jsp/admin/content/addEmail.jsp" />
	</definition>

	<definition name="updateEmail" extends="base.definition">
		<put-attribute name="body" value="/WEB-INF/jsp/admin/content/updateEmail.jsp" />
	</definition>




</tiles-definitions>